Workbook

Sheet NPV
B2: Ежемесячная Ставка дисконтирования, r = | C2: ='Ставка дисконтирования'!C9 -> 0.016708964 | D2: (CAPEX) Инвестиции | E2: ='Оттоки (Расходы)'!D12 -> 113000000
B3: Месяцы | C3: ='Оттоки (Расходы)'!G3 -> 45747 | D3: ='Оттоки (Расходы)'!G4 -> 45777 | E3: ='Оттоки (Расходы)'!G5 -> 45808 | F3: ='Оттоки (Расходы)'!G6 -> 45838 | G3: ='Оттоки (Расходы)'!G7 -> 45869 | H3: ='Оттоки (Расходы)'!G8 -> 45900 | I3: ='Оттоки (Расходы)'!G9 -> 45930 | J3: ='Оттоки (Расходы)'!G10 -> 45961 | K3: ='Оттоки (Расходы)'!G11 -> 45991 | L3: ='Оттоки (Расходы)'!G12 -> 46022 | M3: ='Оттоки (Расходы)'!G13 -> 46053 | N3: ='Оттоки (Расходы)'!G14 -> 46081
C4: 0 | D4: 1 | E4: 2 | F4: 3 | G4: 4 | H4: 5 | I4: 6 | J4: 7 | K4: 8 | L4: 9 | M4: 10 | N4: 11
B5: Притоки | C5: ='Притоки (Доходная часть)'!L3 -> 802500 | D5: ='Притоки (Доходная часть)'!L4 -> 802500 | E5: ='Притоки (Доходная часть)'!L5 -> 802500 | F5: ='Притоки (Доходная часть)'!L6 -> 802500 | G5: ='Притоки (Доходная часть)'!L7 -> 802500 | H5: ='Притоки (Доходная часть)'!L8 -> 802500 | I5: ='Притоки (Доходная часть)'!L9 -> 802500 | J5: ='Притоки (Доходная часть)'!L10 -> 802500 | K5: ='Притоки (Доходная часть)'!L11 -> 802500 | L5: ='Притоки (Доходная часть)'!L12 -> 802500 | M5: ='Притоки (Доходная часть)'!L13 -> 802500 | N5: ='Притоки (Доходная часть)'!L14 -> 155700000
B6: Оттоки | C6: ='Оттоки (Расходы)'!I3 -> -95000000 | D6: ='Оттоки (Расходы)'!I4 -> -3404448.3 | E6: ='Оттоки (Расходы)'!I5 -> -3404448.3 | F6: ='Оттоки (Расходы)'!I6 -> -3404448.3 | G6: ='Оттоки (Расходы)'!I7 -> -3404448.3 | H6: ='Оттоки (Расходы)'!I8 -> -3404448.3 | I6: ='Оттоки (Расходы)'!I9 -> -3404448.3 | J6: ='Оттоки (Расходы)'!I10 -> -404448.28 | K6: ='Оттоки (Расходы)'!I11 -> -404448.28 | L6: ='Оттоки (Расходы)'!I12 -> -404448.28 | M6: ='Оттоки (Расходы)'!I13 -> -404448.28 | N6: ='Оттоки (Расходы)'!I14 -> -404448.28
B7: Чистый денежный поток (FCFF) | C7: =SUM(C5:C6) -> -94197500 | D7: =SUM(D5:D6) -> -2601948.3 | E7: =SUM(E5:E6) -> -2601948.3 | F7: =SUM(F5:F6) -> -2601948.3 | G7: =SUM(G5:G6) -> -2601948.3 | H7: =SUM(H5:H6) -> -2601948.3 | I7: =SUM(I5:I6) -> -2601948.3 | J7: =SUM(J5:J6) -> 398051.72 | ... N7: =SUM(N5:N6) -> 1.5529555e+08
B8: ЧДП нарастающим потоком | C8: =SUM($C$7:C7) -> -94197500 | D8: =SUM($C$7:D7) -> -96799448 | E8: =SUM($C$7:E7) -> -99401397 | F8: =SUM($C$7:F7) -> -1.0200334e+08 | G8: =SUM($C$7:G7) -> -1.0460529e+08 | H8: =SUM($C$7:H7) -> -1.0720724e+08 | I8: =SUM($C$7:I7) -> -1.0980919e+08 | J8: =SUM($C$7:J7) -> -1.0941114e+08 | ... N8: =SUM($C$7:N7) -> 47078569
B9: Фактор | C9: =1/POWER(1+$C$2,C4) -> 1 | D9: =1/POWER(1+$C$2,D4) -> 0.98356564 | E9: =1/POWER(1+$C$2,E4) -> 0.96740136 | F9: =1/POWER(1+$C$2,F4) -> 0.95150274 | G9: =1/POWER(1+$C$2,G4) -> 0.9358654 | H9: =1/POWER(1+$C$2,H4) -> 0.92048505 | I9: =1/POWER(1+$C$2,I4) -> 0.90535746 | J9: =1/POWER(1+$C$2,J4) -> 0.89047849 | ... N9: =1/POWER(1+$C$2,N4) -> 0.833368
B10: Притоки (дисконтированные) | C10: =C5*C9 -> 802500 | D10: =D5*D9 -> 789311.42 | E10: =E5*E9 -> 776339.59 | F10: =F5*F9 -> 763580.95 | G10: =G5*G9 -> 751031.98 | H10: =H5*H9 -> 738689.25 | I10: =I5*I9 -> 726549.36 | J10: =J5*J9 -> 714608.99 | ... N10: =N5*N9 -> 1.297554e+08
B11: Оттоки (дисконтированные) | C11: =C6*C9 -> -95000000 | D11: =D6*D9 -> -3348498.3 | E11: =E6*E9 -> -3293467.9 | F11: =F6*F9 -> -3239341.9 | G11: =G6*G9 -> -3186105.3 | H11: =H6*H9 -> -3133743.7 | I11: =I6*I9 -> -3082242.6 | J11: =J6*J9 -> -360152.49 | ... N11: =N6*N9 -> -337054.25
B12: Дсконтированный чистый денежный поток (DFCFF) | C12: =SUM(C10:C11) -> -94197500 | D12: =SUM(D10:D11) -> -2559186.9 | E12: =SUM(E10:E11) -> -2517128.3 | F12: =SUM(F10:F11) -> -2475760.9 | G12: =SUM(G10:G11) -> -2435073.4 | H12: =SUM(H10:H11) -> -2395054.5 | I12: =SUM(I10:I11) -> -2355693.3 | J12: =SUM(J10:J11) -> 354456.5 | ... N12: =SUM(N10:N11) -> 1.2941834e+08
B13: Дисконтированный чистый денежный поток нарастающим потоком | C13: =SUM($C$12:C12) -> -94197500 | D13: =SUM($C$12:D12) -> -96756687 | E13: =SUM($C$12:E12) -> -99273815 | F13: =SUM($C$12:F12) -> -1.0174958e+08 | G13: =SUM($C$12:G12) -> -1.0418465e+08 | H13: =SUM($C$12:H12) -> -1.065797e+08 | I13: =SUM($C$12:I12) -> -1.089354e+08 | J13: =SUM($C$12:J12) -> -1.0858094e+08 | ... N13: =SUM($C$12:N12) -> 21866202
B15: Финансовые показатели:
B16: NOI (Чистый операционный доход объекта за вычетом операционных расходов, без учета кредита, налогов на прибыль и амортизации) | C16: ='Притоки (Доходная часть)'!F21 - ABS('Оттоки (Расходы)'!F10)*12 -> 4776620.7 | D16: в год
B17: Cap rate (Ставка капитализации — по ней считают стоимость) | C17: =C16 / 'Оттоки (Расходы)'!F3 -> 0.050280218
B18: Vacancy rate (Уровень вакантности (доля пустующих площадей)) | C18: =1-(SUMIF('Притоки (Доходная часть)'!D3:D20, ">0", 'Притоки (Доходная часть)'!C3:C20)/SUM('Притоки (Доходная часть)'!C3:C20)) -> 0.072254335
B19: NPV (чистый приведенный доход) | C19: =XNPV('Ставка дисконтирования'!C3,C7:N7,C3:N3) -> 21908022 | D19: =IF(C19<0, "Не подходит", "Подходит") -> Подходит
B20: IRR (внутренняя норма доходности проекта) | C20: =XIRR(C7:N7,C3:N3,) -> 0.50417455 | D20: =IF(C20<0, "Не подходит", "Подходит") -> Подходит
B21: PI (индекс доходности - индикатор относительной прибыльности проекта) | C21: =(C19+E2)/E2 -> 1.1938763 | D21: =IF(C21<1, "Не инвестировать", "Инвестировать") -> Инвестировать
B22: PP (payback period - период окупаемости вложений) | C22: =MAX(C25:N25) -> 10.696845 | D22: мес.
B23: DPP (кол. Мес.) | C23: =MAX(C26:N26) -> 10.831042 | D23: мес.
B24: ROI коэффициент возврата инвестиций | C24: =N8/E2 -> 0.4166245
B25: PP | C25: =IF(AND(C8>0,B8<0),B4+(1-C8/C7),"") | D25: =IF(AND(D8>0,C8<0),C4+(1-D8/D7),"") | E25: =IF(AND(E8>0,D8<0),D4+(1-E8/E7),"") | F25: =IF(AND(F8>0,E8<0),E4+(1-F8/F7),"") | G25: =IF(AND(G8>0,F8<0),F4+(1-G8/G7),"") | H25: =IF(AND(H8>0,G8<0),G4+(1-H8/H7),"") | I25: =IF(AND(I8>0,H8<0),H4+(1-I8/I7),"") | J25: =IF(AND(J8>0,I8<0),I4+(1-J8/J7),"") | ... N25: =IF(AND(N8>0,M8<0),M4+(1-N8/N7),"") -> 10.696845
B26: DPP | C26: =IF(AND(C13>0,B13<0),B4+(1-C13/C12),"") | D26: =IF(AND(D13>0,C13<0),C4+(1-D13/D12),"") | E26: =IF(AND(E13>0,D13<0),D4+(1-E13/E12),"") | F26: =IF(AND(F13>0,E13<0),E4+(1-F13/F12),"") | G26: =IF(AND(G13>0,F13<0),F4+(1-G13/G12),"") | H26: =IF(AND(H13>0,G13<0),G4+(1-H13/H12),"") | I26: =IF(AND(I13>0,H13<0),H4+(1-I13/I12),"") | J26: =IF(AND(J13>0,I13<0),I4+(1-J13/J12),"") | ... N26: =IF(AND(N13>0,M13<0),M4+(1-N13/N12),"") -> 10.831042

Sheet Ставка дисконтирования
B2: Инфляция на 2025 г. | C2: 0
B3: Стоимость собственного капитала | C3: 0.22 | D3: %
B4: Стоимость долгового капитала компании
B5: Премия за риск
B6: ROE | C6: ='Притоки (Доходная часть)'!L13/'Оттоки (Расходы)'!I18*100 -> #DIV/0!
B7: ROA | C7: ='Притоки (Доходная часть)'!L13/'Оттоки (Расходы)'!I18 -> #DIV/0!
B9: Discount rate (ежемесячно) | C9: =(1+C3)^(1/12)-1 -> 0.016708964

Sheet Оттоки (Расходы)
C2: Инвестиции | H2: Период | I2: Чистый денежный поток (CF)
C3: Покупка здания | F3: 95000000 | G3: 45747 | H3: 45747 | I3: =L3 -> -95000000 | K3: 45747 | L3: =-F3 -> -95000000
B4: OPEX | C4: Зарплата штатному персоналу | F4: ='Штатная структура'!H10 -> 369448.28 | G4: 45777 | H4: 45777 | I4: =L4 -> -3404448.3 | K4: 45777 | L4: =$F$9 -> -3404448.3
C5: Коммунальные платежи ежемесячно | F5: =Коммуналка!H13 -> 35000 | G5: 45808 | H5: 45808 | I5: =L5 -> -3404448.3 | K5: 45808 | L5: =$F$9 -> -3404448.3
C6: Подведение коммуникаций | F6: ='Подведение коммуникаций'!E12 -> 0 | G6: 45838 | H6: 45838 | I6: =L6 -> -3404448.3 | K6: 45838 | L6: =$F$9 -> -3404448.3
C7: РЕМОНТ | E7: за 6 месяцев | F7: 18000000 | G7: 45869 | H7: 45869 | I7: =L7 -> -3404448.3 | K7: 45869 | L7: =$F$9 -> -3404448.3
E8: каждый мес. | F8: =F7/6 -> 3000000 | G8: 45900 | H8: 45900 | I8: =L8 -> -3404448.3 | K8: 45900 | L8: =$F$9 -> -3404448.3
C9: Общий ежемесячный расход на операционку | F9: =-SUM(F4,F5,F8) -> -3404448.3 | G9: 45930 | H9: 45930 | I9: =L9 -> -3404448.3 | K9: 45930 | L9: =$F$9 -> -3404448.3
C10: ИТОГО | D10: =SUM(F4:F5) -> 404448.28 | E10: =D10*12 -> 4853379.3 | F10: =-SUM(F4,F6,F5) -> -404448.28 | G10: 45961 | H10: 45961 | I10: =L10 -> -404448.28 | K10: 45961 | L10: =$F$10 -> -404448.28
C11: Суммарные инвестиции | G11: 45991 | H11: 45991 | I11: =L11 -> -404448.28 | K11: 45991 | L11: =$F$10 -> -404448.28
B12: CAPEX | C12: ИТОГО | D12: =F3+F6+F7 -> 113000000 | G12: 46022 | H12: 46022 | I12: =L12 -> -404448.28 | K12: 46022 | L12: =$F$10 -> -404448.28
G13: 46053 | H13: 46053 | I13: =L13 -> -404448.28 | K13: 46053 | L13: =$F$10 -> -404448.28
G14: 46081 | H14: 46081 | I14: =L14 -> -404448.28 | K14: 46081 | L14: =$F$10 -> -404448.28
G15: 46112 | H15: 46112 | I15: =L15 -> 0 | K15: 46112
G16: 46142 | H16: 46142 | I16: =L16 -> 0 | K16: 46142
G17: 46173 | H17: 46173 | I17: =L17 -> 0 | K17: 46173
G18: 46203 | H18: 46203 | I18: =L18 -> 0 | K18: 46203
G19: 46234 | H19: 46234 | I19: =L19 -> 0 | K19: 46234
G20: 46265 | H20: 46265 | I20: =L20 -> 0 | K20: 46265
G21: 46295 | H21: 46295 | I21: =L21 -> 0 | K21: 46295
G22: 46326 | H22: 46326 | I22: =L22 -> 0 | K22: 46326
G23: 46356 | H23: 46356 | I23: =L23 -> 0 | K23: 46356
G24: 46387 | H24: 46387 | I24: =L24 -> 0 | K24: 46387
G25: 46418 | H25: 46418 | I25: =L25 -> 0 | K25: 46418
G26: 46446 | H26: 46446 | I26: =L26 -> 0 | K26: 46446
... G36: 46752 | H36: 46752 | I36: =L36 -> 0 | K36: 46752
I37: =SUM(I3:I14) -> -1.1744893e+08

Sheet Подведение коммуникаций
B2: Для выбранного объекто рассмотрим вариант с подведением электричества.
B3: Водоснабжение/водоотведение, теплоснабжение подводить не будем.
B4: Отопление будет электрическим.
B6: Расчет подведения эл-ва до 150 кВт
C8: усл./метр/шт.
B9: выдача технических условий | C9: 1 | D9: 0 | E9: =D9*C9 -> 0
B10: строительство линии электропередач длиной | C10: 250 | D10: 0 | E10: =D10*C10 -> 0
B11: прибор учета | C11: 1 | D11: 0 | E11: =D11*C11 -> 0
D12: Итого с учетом НДС | E12: =SUM(E9:E11) -> 0

Sheet Штатная структура
A1: № | B1: должность | C1: ФИО / вакансия | D1: блок | E1: зарплата
E2: фикс | F2: бонус | G2: итого | H2: с учетом налогов
B3: Моя зарплата | G3: 160000 | H3: =G3 / (1 - 0.13) * 1.302 -> 239448.28
A4: 1 | B4: Охранник | E4: 50000 | H4: 0
A5: 2 | B5: Охранник | E5: 60000 | H5: 100000
A6: 3 | B6: Обслуживание противопожарной системы безопасности | H6: 10000
A7: 4 | B7: Вывоз ТБО | H7: 10000
A8: 5 | B8: Обслуживание ИТП | H8: 10000
A9: 6 | B9: Клининг | H9: 0
H10: =SUM(H3:H9) -> 369448.28

Sheet Коммуналка
A3: Расчет расходов Заказчика на электричество
F5: показ сч общ | H5: =24283/15 -> 1618.8667 | I5: кВт
C6: 2025 г. | F6: общ плата в МЭС | H6: 35000 | I6: руб.
C7: расчетный месяц | F7: тариф Тэ | H7: 6.8228876 | I7: руб.
A9: № | B9: блок | C9: Собственник | D9: Арендатор Собствнника | E9: S по свид. | F9: Sсч | G9: Sбсч | H9: Эcч | I9: Эбcч | J9: Э*Тэ | K9: Эмоп*Д*Тэ | L9: Д | M9: Сумма к оплате, руб.
F10: Площади оборудованные счетчиками | G10: Площади не оборудованные счетчиками | H10: Расход Э/Э по счет,кВт | I10: Расход Э/Э без счет, кВт | J10: затраты на содержание , руб | K10: затраты на содержание МОП, руб | L10: Доля в строении, %
G13: Итого | H13: =SUM(H6) -> 35000

Sheet Притоки (Доходная часть)
A2: АРЕНДА | B2: этаж | C2: Метраж | D2: Ставка за 1м2 | E2: МАП | F2: ГАП | G2: 5% ндс | H2: ГАП+налог | J2: Даты | K2: Период | L2: Чистый денежный поток (CF)
B3: 1 | C3: 12 | D3: 30000 | E3: =D3*C3/12 -> 30000 | F3: =E3*12 -> 360000 | G3: =F3/100*6 -> 21600 | H3: =F3+G3 -> 381600 | J3: 45747 | K3: 0 | L3: =$E$21 -> 802500
B4: 1 | C4: 12 | D4: 30000 | E4: =D4*C4/12 -> 30000 | F4: =E4*12 -> 360000 | G4: =F4/100*6 -> 21600 | H4: =F4+G4 -> 381600 | J4: 45777 | K4: 1 | L4: =$E$21 -> 802500
B5: 1 | C5: 12 | D5: 30000 | E5: =D5*C5/12 -> 30000 | F5: =E5*12 -> 360000 | G5: =F5/100*6 -> 21600 | H5: =F5+G5 -> 381600 | J5: 45808 | K5: 2 | L5: =$E$21 -> 802500
B6: 1 | C6: 12 | D6: 30000 | E6: =D6*C6/12 -> 30000 | F6: =E6*12 -> 360000 | G6: =F6/100*6 -> 21600 | H6: =F6+G6 -> 381600 | J6: 45838 | K6: 3 | L6: =$E$21 -> 802500
B7: 1 | C7: 12 | D7: 30000 | E7: =D7*C7/12 -> 30000 | F7: =E7*12 -> 360000 | G7: =F7/100*6 -> 21600 | H7: =F7+G7 -> 381600 | J7: 45869 | K7: 4 | L7: =$E$21 -> 802500
B8: 1 | C8: 12 | D8: 30000 | E8: =D8*C8/12 -> 30000 | F8: =E8*12 -> 360000 | G8: =F8/100*6 -> 21600 | H8: =F8+G8 -> 381600 | J8: 45900 | K8: 5 | L8: =$E$21 -> 802500
B9: 1 | C9: 12 | D9: 30000 | E9: =D9*C9/12 -> 30000 | F9: =E9*12 -> 360000 | G9: =F9/100*6 -> 21600 | H9: =F9+G9 -> 381600 | J9: 45930 | K9: 6 | L9: =$E$21 -> 802500
B10: 1 | C10: 12 | D10: 30000 | E10: =D10*C10/12 -> 30000 | F10: =E10*12 -> 360000 | G10: =F10/100*6 -> 21600 | H10: =F10+G10 -> 381600 | J10: 45961 | K10: 7 | L10: =$E$21 -> 802500
B11: 2 | C11: 25 | D11: 30000 | E11: =D11*C11/12 -> 62500 | F11: =E11*12 -> 750000 | G11: =F11/100*6 -> 45000 | H11: =F11+G11 -> 795000 | J11: 45991 | K11: 8 | L11: =$E$21 -> 802500
B12: 2 | C12: 25 | D12: 30000 | E12: =D12*C12/12 -> 62500 | F12: =E12*12 -> 750000 | G12: =F12/100*6 -> 45000 | H12: =F12+G12 -> 795000 | J12: 46022 | K12: 9 | L12: =$E$21 -> 802500
B13: 2 | C13: 25 | D13: 30000 | E13: =D13*C13/12 -> 62500 | F13: =E13*12 -> 750000 | G13: =F13/100*6 -> 45000 | H13: =F13+G13 -> 795000 | J13: 46053 | K13: 10 | L13: =$E$21 -> 802500
B14: 2 | C14: 25 | D14: 30000 | E14: =D14*C14/12 -> 62500 | F14: =E14*12 -> 750000 | G14: =F14/100*6 -> 45000 | H14: =F14+G14 -> 795000 | J14: 46081 | K14: 11 | L14: =E23 -> 155700000
B15: 2 | C15: 25 | D15: 30000 | E15: =D15*C15/12 -> 62500 | F15: =E15*12 -> 750000 | G15: =F15/100*6 -> 45000 | H15: =F15+G15 -> 795000 | J15: 46112 | K15: 12 | L15: 0
B16: 2 | C16: 25 | D16: 30000 | E16: =D16*C16/12 -> 62500 | F16: =E16*12 -> 750000 | G16: =F16/100*6 -> 45000 | H16: =F16+G16 -> 795000 | J16: 46142 | K16: 13 | L16: 0
B17: 2 | C17: 25 | D17: 30000 | E17: =D17*C17/12 -> 62500 | F17: =E17*12 -> 750000 | G17: =F17/100*6 -> 45000 | H17: =F17+G17 -> 795000 | J17: 46173 | K17: 14 | L17: 0
B18: 2 | C18: 25 | D18: 30000 | E18: =D18*C18/12 -> 62500 | F18: =E18*12 -> 750000 | G18: =F18/100*6 -> 45000 | H18: =F18+G18 -> 795000 | J18: 46203 | K18: 15 | L18: 0
B19: 2 | C19: 25 | D19: 30000 | E19: =D19*C19/12 -> 62500 | F19: =E19*12 -> 750000 | G19: =F19/100*6 -> 45000 | H19: =F19+G19 -> 795000 | J19: 46234 | K19: 16 | L19: 0
B20: 2 | C20: 25 | D20: 0 | E20: =D20*C20/12 -> 0 | F20: =E20*12 -> 0 | G20: =F20/100*6 -> 0 | H20: =F20+G20 -> 0 | J20: 46265 | K20: 17 | L20: 0
B21: Арендопригодная площадь | C21: =SUM(C3:C20) -> 346 | E21: =SUM(E3:E20) -> 802500 | F21: =SUM(F3:F20) -> 9630000 | G21: =F21/100*6 -> 577800 | H21: =F21+G21 -> 10207800 | J21: 46295 | K21: 18 | L21: 0
A22: ПРОДАЖА | B22: ПРОДАЖА | J22: 46326 | K22: 19 | L22: 0
B23: Здание | C23: =C21 -> 346 | D23: 450000 | E23: =D23*C23 -> 155700000 | J23: 46356 | K23: 20 | L23: 0
J24: 46387 | K24: 21 | L24: 0
J25: 46418 | K25: 22 | L25: 0
J26: 46446 | K26: 23 | L26: 0
J27: 46477 | K27: 24
J28: 46507 | K28: 25
J29: 46538 | K29: 26
J30: 46568 | K30: 27
J31: 46599 | K31: 28
J32: 46630 | K32: 29
J33: 46660 | K33: 30
J34: 46691 | K34: 31
J35: 46721 | K35: 32
J36: 46752 | K36: 33
J37: 46783 | K37: 34
J38: 46812 | K38: 35
... J181: 51166 | K181: 178
